{
  "date": "2026-04-04",
  "total_players_ranked": 306,
  "total_hrs_hit": 17,
  "total_near_hrs": 0,
  "model_hits": 15,
  "best_lookback": "L5",
  "tier_accuracy_by_lookback": {
    "L5": {
      "top_10": {
        "total": 10,
        "hits": 2,
        "rate": 20.0
      },
      "top_20": {
        "total": 20,
        "hits": 2,
        "rate": 10.0
      },
      "top_30": {
        "total": 30,
        "hits": 3,
        "rate": 10.0
      },
      "all": {
        "total": 306,
        "hits": 15,
        "rate": 4.9
      }
    },
    "L10": {
      "top_10": {
        "total": 10,
        "hits": 2,
        "rate": 20.0
      },
      "top_20": {
        "total": 20,
        "hits": 2,
        "rate": 10.0
      },
      "top_30": {
        "total": 30,
        "hits": 3,
        "rate": 10.0
      },
      "all": {
        "total": 306,
        "hits": 15,
        "rate": 4.9
      }
    }
  },
  "model_near_hits": 0,
  "tier_accuracy": {
    "top_10": {
      "total": 10,
      "hits": 2,
      "rate": 20.0
    },
    "top_20": {
      "total": 20,
      "hits": 2,
      "rate": 10.0
    },
    "top_30": {
      "total": 30,
      "hits": 3,
      "rate": 10.0
    },
    "all": {
      "total": 306,
      "hits": 15,
      "rate": 4.9
    }
  },
  "tier_accuracy_with_near": {
    "top_10": {
      "total": 10,
      "hits": 2,
      "rate": 20.0
    },
    "top_20": {
      "total": 20,
      "hits": 2,
      "rate": 10.0
    },
    "top_30": {
      "total": 30,
      "hits": 3,
      "rate": 10.0
    },
    "all": {
      "total": 306,
      "hits": 15,
      "rate": 4.9
    }
  },
  "avg_composite_hr_hitters": 0.284,
  "avg_composite_non_hitters": 0.271,
  "composite_separation": 0.013,
  "hr_hitters": [
    {
      "name": "Salvador Perez",
      "rank": 5,
      "composite": 0.562,
      "opp_pitcher": "Brandon Sproat",
      "matchup": "MIL@KC"
    },
    {
      "name": "Christian Walker",
      "rank": 9,
      "composite": 0.538,
      "opp_pitcher": "Luis Morales",
      "matchup": "HOU@ATH"
    },
    {
      "name": "Andy Pages",
      "rank": 27,
      "composite": 0.442,
      "opp_pitcher": "Jake Irvin",
      "matchup": "LAD@WSH"
    },
    {
      "name": "CJ Abrams",
      "rank": 81,
      "composite": 0.335,
      "opp_pitcher": "Tyler Glasnow",
      "matchup": "LAD@WSH"
    },
    {
      "name": "Kerry Carpenter",
      "rank": 101,
      "composite": 0.302,
      "opp_pitcher": "Dustin May",
      "matchup": "STL@DET"
    },
    {
      "name": "Zach Neto",
      "rank": 123,
      "composite": 0.277,
      "opp_pitcher": "Emerson Hancock",
      "matchup": "SEA@LAA"
    },
    {
      "name": "Jordan Walker",
      "rank": 134,
      "composite": 0.263,
      "opp_pitcher": "Jack Flaherty",
      "matchup": "STL@DET"
    },
    {
      "name": "Gleyber Torres",
      "rank": 145,
      "composite": 0.25,
      "opp_pitcher": "Dustin May",
      "matchup": "STL@DET"
    },
    {
      "name": "Zach McKinstry",
      "rank": 146,
      "composite": 0.25,
      "opp_pitcher": "Dustin May",
      "matchup": "STL@DET"
    },
    {
      "name": "Vladimir Guerrero Jr.",
      "rank": 176,
      "composite": 0.224,
      "opp_pitcher": "Grant Taylor",
      "matchup": "TOR@CWS"
    },
    {
      "name": "Garrett Mitchell",
      "rank": 218,
      "composite": 0.199,
      "opp_pitcher": "Seth Lugo",
      "matchup": "MIL@KC"
    },
    {
      "name": "Colson Montgomery",
      "rank": 246,
      "composite": 0.177,
      "opp_pitcher": "Mason Fluharty",
      "matchup": "TOR@CWS"
    },
    {
      "name": "Cody Bellinger",
      "rank": 247,
      "composite": 0.176,
      "opp_pitcher": "Max Meyer",
      "matchup": "MIA@NYY"
    },
    {
      "name": "Munetaka Murakami",
      "rank": 283,
      "composite": 0.141,
      "opp_pitcher": "Mason Fluharty",
      "matchup": "TOR@CWS"
    },
    {
      "name": "Tyrone Taylor",
      "rank": 289,
      "composite": 0.13,
      "opp_pitcher": "Landen Roupp",
      "matchup": "NYM@SF"
    }
  ],
  "near_hr_hitters": [],
  "near_hr_events": [],
  "surprise_hrs": [
    {
      "name": "Matt Vierling",
      "pitcher": "Chris Roycroft",
      "description": "Matt Vierling homers (1) on a fly ball to right field. Spencer Torkelson scores."
    },
    {
      "name": "Cam Smith",
      "pitcher": "Luis Medina",
      "description": "Cam Smith homers (2) on a fly ball to left center field."
    }
  ]
}